ml4gw/__init__.py
ml4gw/augmentations.py
ml4gw/constants.py
ml4gw/distributions.py
ml4gw/gw.py
ml4gw/spectral.py
ml4gw/types.py
ml4gw/dataloading/__init__.py
ml4gw/dataloading/chunked_dataset.py
ml4gw/dataloading/hdf5_dataset.py
ml4gw/dataloading/in_memory_dataset.py
ml4gw/nn/__init__.py
ml4gw/nn/norm.py
ml4gw/nn/autoencoder/__init__.py
ml4gw/nn/autoencoder/base.py
ml4gw/nn/autoencoder/convolutional.py
ml4gw/nn/autoencoder/skip_connection.py
ml4gw/nn/autoencoder/utils.py
ml4gw/nn/resnet/__init__.py
ml4gw/nn/resnet/resnet_1d.py
ml4gw/nn/resnet/resnet_2d.py
ml4gw/nn/streaming/__init__.py
ml4gw/nn/streaming/online_average.py
ml4gw/nn/streaming/snapshotter.py
ml4gw/transforms/__init__.py
ml4gw/transforms/decimator.py
ml4gw/transforms/iirfilter.py
ml4gw/transforms/pearson.py
ml4gw/transforms/qtransform.py
ml4gw/transforms/scaler.py
ml4gw/transforms/snr_rescaler.py
ml4gw/transforms/spectral.py
ml4gw/transforms/spectrogram.py
ml4gw/transforms/spline_interpolation.py
ml4gw/transforms/transform.py
ml4gw/transforms/waveforms.py
ml4gw/transforms/whitening.py
ml4gw/utils/interferometer.py
ml4gw/utils/slicing.py
ml4gw/waveforms/__init__.py
ml4gw/waveforms/conversion.py
ml4gw/waveforms/generator.py
ml4gw/waveforms/adhoc/__init__.py
ml4gw/waveforms/adhoc/ringdown.py
ml4gw/waveforms/adhoc/sine_gaussian.py
ml4gw/waveforms/cbc/__init__.py
ml4gw/waveforms/cbc/coefficients.py
ml4gw/waveforms/cbc/phenom_d.py
ml4gw/waveforms/cbc/phenom_d_data.py
ml4gw/waveforms/cbc/phenom_p.py
ml4gw/waveforms/cbc/taylorf2.py
ml4gw/waveforms/cbc/utils.py
ml4gw-0.7.11.dist-info/licenses/LICENSE
ml4gw-0.7.11.dist-info/METADATA
ml4gw-0.7.11.dist-info/WHEEL
ml4gw-0.7.11.dist-info/top_level.txt
ml4gw-0.7.11.dist-info/RECORD
