Metadata-Version: 2.4
Name: ml4gw
Version: 0.7.11
Summary: Tools for training torch models on gravitational wave data
Author-email: Ethan Marx <emarx@mit.edu>, Will Benoit <benoi090@umn.edu>, Deep Chatterjee <deep1018@mit.edu>, Alec Gunny <alec.gunny@ligo.org>, Ravi Kumar <ravi.kumar@ligo.org>
Maintainer-email: Ethan Marx <emarx@mit.edu>, Will Benoit <benoi090@umn.edu>, Deep Chatterjee <deep1018@mit.edu>
License-Expression: GPL-3.0-or-later
Classifier: Programming Language :: Python :: 3.10
Classifier: Programming Language :: Python :: 3.11
Classifier: Programming Language :: Python :: 3.12
Classifier: Topic :: Scientific/Engineering :: Astronomy
Classifier: Topic :: Scientific/Engineering :: Physics
Requires-Python: <3.13,>=3.10
License-File: LICENSE
Requires-Dist: jaxtyping<0.3,>=0.2
Requires-Dist: torch~=2.0
Requires-Dist: torchaudio~=2.0
Requires-Dist: numpy>=1.0.0
Requires-Dist: scipy<1.15,>=1.9.0
Dynamic: license-file
